Metadata-Version: 1.0
Name: gmm-mml
Version: 0.12
Summary: Unsupervised cluster selection for finite guassian mixture models
Home-page: https://github.com/abriosi/gmm-mml/
Author: abriosi
Author-email: UNKNOWN
License: MIT
Platform: UNKNOWN
